mezzanine_pagedown/__init__.py
mezzanine_pagedown/defaults.py
mezzanine_pagedown/fields.py
mezzanine_pagedown/filters.py
mezzanine_pagedown/models.py
mezzanine_pagedown/urls.py
mezzanine_pagedown/views.py
mezzanine_pagedown/widgets.py
mezzanine_pagedown/management/__init__.py
mezzanine_pagedown/management/commands/__init__.py
mezzanine_pagedown/management/commands/pygments_styles.py
mezzanine_pagedown/static/mezzanine_pagedown/css/pagedown.css
mezzanine_pagedown/static/mezzanine_pagedown/js/jquery.ba-throttle-debounce.min.js
mezzanine_pagedown/static/mezzanine_pagedown/js/jquery.cookie.js
mezzanine_pagedown/static/mezzanine_pagedown/pagedown/LICENSE.txt
mezzanine_pagedown/static/mezzanine_pagedown/pagedown/Markdown.Converter.js
mezzanine_pagedown/static/mezzanine_pagedown/pagedown/Markdown.Editor.js
mezzanine_pagedown/static/mezzanine_pagedown/pagedown/Markdown.Sanitizer.js
mezzanine_pagedown/static/mezzanine_pagedown/pagedown/wmd-buttons.png
mezzanine_pagedown/templates/mezzanine_pagedown/editor.html
mezzanine_pagedown-1.5.dist-info/LICENSE
mezzanine_pagedown-1.5.dist-info/METADATA
mezzanine_pagedown-1.5.dist-info/WHEEL
mezzanine_pagedown-1.5.dist-info/top_level.txt
mezzanine_pagedown-1.5.dist-info/RECORD
