Metadata-Version: 2.1
Name: mezzanine-pagedown
Version: 1.5
Summary: PageDown rich text widget for Mezzanine
Home-page: https://bitbucket.org/akhayyat/mezzanine-pagedown
Author: Ahmad Khayyat
Author-email: akhayyat@gmail.com
License: BSD
Platform: UNKNOWN
Classifier: Development Status :: 4 - Beta
Classifier: Intended Audience :: Developers
Classifier: License :: OSI Approved :: BSD License
Classifier: Operating System :: OS Independent
Classifier: Programming Language :: Python
Classifier: Programming Language :: JavaScript
Classifier: Framework :: Django
License-File: LICENSE
Requires-Dist: setuptools
Requires-Dist: filebrowser-safe (>=0.2.13)
Requires-Dist: mezzanine (>=1.4.4)
Requires-Dist: markdown
Requires-Dist: bleach
